ex03/src/debouncer.vhd
LIBRARY IEEE;
USE IEEE.STD_LOGIC_1164.ALL;
USE IEEE.NUMERIC_STD.ALL;

ENTITY debouncer IS
    PORT (
        clk     : IN STD_LOGIC; -- 100 MHz board clock
        btn_in  : IN STD_LOGIC; -- Bouncy mechanical output
        btn_out : OUT STD_LOGIC -- Clean debounced output
    );
END debouncer;

ARCHITECTURE behavioral OF debouncer IS
    -- Counter for the 1 MHz clock we use to enable (7 bits for 0 to 99)
    SIGNAL clk_div_cnt : INTEGER RANGE 0 TO 99        := 0;
    SIGNAL tick_1MHz   : STD_LOGIC                    := '0';

    -- 8 bit history register (button must be stable for at least
    -- 8 microseconds before being registered as a valid press)
    SIGNAL shift_reg   : STD_LOGIC_VECTOR(7 DOWNTO 0) := (OTHERS => '0');
BEGIN

    -- Clock divider process
    PROCESS (clk)
    BEGIN
        IF rising_edge(clk) THEN
            IF clk_div_cnt = 99 THEN
                clk_div_cnt <= 0;
                tick_1MHz   <= '1';
            ELSE
                clk_div_cnt <= clk_div_cnt + 1;
                tick_1MHz   <= '0';
            END IF;
        END IF;
    END PROCESS;

    -- Shift register process
    PROCESS (clk)
    BEGIN
        IF rising_edge(clk) THEN
            -- We only shift when the 1 MHz tick is fired
            -- Because our shift reg is 8 bits long and each bit is only
            -- shifted every 1 microsecond, we induce a latency of 8 microseconds
            IF tick_1MHz = '1' THEN
                shift_reg <= shift_reg(6 DOWNTO 0) & (btn_in);
            END IF;
        END IF;
    END PROCESS;

    -- Output logic
    -- Equivalent to reduction AND compatible with older VHDL modes
    btn_out <= '1' WHEN shift_reg = x"FF" ELSE
        '0';

END behavioral;

ex03/tb/debouncer_tb.vhd
LIBRARY IEEE;
USE IEEE.STD_LOGIC_1164.ALL;
USE IEEE.NUMERIC_STD.ALL;

ENTITY debouncer_tb IS
END debouncer_tb;

ARCHITECTURE sim OF debouncer_tb IS
    COMPONENT debouncer
        PORT (
            clk     : IN STD_LOGIC;
            btn_in  : IN STD_LOGIC;
            btn_out : OUT STD_LOGIC
        );
    END COMPONENT;

    -- Local signals
    SIGNAL tb_clk       : STD_LOGIC := '0';
    SIGNAL tb_btn_in    : STD_LOGIC := '0';
    SIGNAL tb_btn_out   : STD_LOGIC;

    -- 100 MHz clock period means 10 ns
    CONSTANT CLK_PERIOD : TIME := 10 ns;

BEGIN
    -- Instantiate design under test (DUT)
    dut : debouncer PORT MAP(
        clk     => tb_clk,
        btn_in  => tb_btn_in,
        btn_out => tb_btn_out
    );

    -- Clock gneneration
    clk_process : PROCESS
    BEGIN
        tb_clk <= '0';
        WAIT FOR CLK_PERIOD / 2; -- 5 ns
        tb_clk <= '1';
        WAIT FOR CLK_PERIOD / 2; -- 5 ns
    END PROCESS;

    -- Bouncy stimulus process
    stim_proc : PROCESS IS
        -- Procedure to simulate bouncy button press
        PROCEDURE press_button_with_bounce IS
        BEGIN
            tb_btn_in <= '1';
            WAIT FOR 400 ns;
            tb_btn_in <= '0';
            WAIT FOR 200 ns;
            tb_btn_in <= '1';
            WAIT FOR 500 ns;
            tb_btn_in <= '0';
            WAIT FOR 300 ns;
            tb_btn_in <= '1'; -- Final stable pressed state
        END PROCEDURE;

        -- Procedure to simulate bouncy button release
        PROCEDURE release_button_with_bounce IS
        BEGIN
            tb_btn_in <= '0';
            WAIT FOR 300 ns;
            tb_btn_in <= '1';
            WAIT FOR 200 ns;
            tb_btn_in <= '0';
            WAIT FOR 400 ns;
            tb_btn_in <= '0'; -- Final stable released state
        END PROCEDURE;
    BEGIN

        -- We start with the button not pressed
        tb_btn_in <= '0';
        WAIT FOR 100 ns;

        -- Now simulate the press of the button
        -- The physical metal springs would make erratic contact
        -- This means our waiting time is chosen randomly here
        -- as defined in our procedure
        press_button_with_bounce;

        -- Finally, the button down would be pressed down properly
        -- We hold this button press for 15 microseconds. 
        -- Since it takes 8 us for the shift register to fill up completely
        WAIT FOR 15 us;

        -- Now simulate the release of the button,
        -- which causes the spring to bounce eratically as well
        release_button_with_bounce;

        -- Now release fully
        WAIT FOR 10 us;

        REPORT "Debouncer Simulation Complete!";

        -- Stop the simulation 
        -- Otherwise the clock process runs forever
        std.env.stop;
    END PROCESS;

END sim;

ex03/scripts/debouncer.vcd
$date
   Sun May 24 01:04:30 2026
$end

$version
  2023.2
$end

$timescale
  1ps
$end

$scope module debouncer_tb $end
$var wire 1 ! tb_clk $end
$var wire 1 " tb_btn_in $end
$var wire 1 # tb_btn_out $end
$scope module dut $end
$var wire 1 ! clk $end
$var wire 1 " btn_in $end
$var wire 1 # btn_out $end
$var wire 1 $ tick_1MHz $end
$var wire 8 % shift_reg $end
$upscope $end
$upscope $end
$enddefinitions $end

#1000000
$dumpvars
0!
1"
0#
1$
b0 %
$end

#1005000
1!
0$
b1 %

#1010000
0!

#1015000
1!

#1020000
0!

#1025000
1!

#1030000
0!

#1035000
1!

#1040000
0!

#1045000
1!

#1050000
0!

#1055000
1!

#1060000
0!

#1065000
1!

#1070000
0!

#1075000
1!

#1080000
0!

#1085000
1!

#1090000
0!

#1095000
1!

#1100000
0!

#1105000
1!

#1110000
0!

#1115000
1!

#1120000
0!

#1125000
1!

#1130000
0!

#1135000
1!

#1140000
0!

#1145000
1!

#1150000
0!

#1155000
1!

#1160000
0!

#1165000
1!

#1170000
0!

#1175000
1!

#1180000
0!

#1185000
1!

#1190000
0!

#1195000
1!

#1200000
0!
0"

#1205000
1!

#1210000
0!

#1215000
1!

#1220000
0!

#1225000
1!

#1230000
0!

#1235000
1!

#1240000
0!

#1245000
1!

#1250000
0!

#1255000
1!

#1260000
0!

#1265000
1!

#1270000
0!

#1275000
1!

#1280000
0!

#1285000
1!

#1290000
0!

#1295000
1!

#1300000
0!

#1305000
1!

#1310000
0!

#1315000
1!

#1320000
0!

#1325000
1!

#1330000
0!

#1335000
1!

#1340000
0!

#1345000
1!

#1350000
0!

#1355000
1!

#1360000
0!

#1365000
1!

#1370000
0!

#1375000
1!

#1380000
0!

#1385000
1!

#1390000
0!

#1395000
1!

#1400000
0!

#1405000
1!

#1410000
0!

#1415000
1!

#1420000
0!

#1425000
1!

#1430000
0!

#1435000
1!

#1440000
0!

#1445000
1!

#1450000
0!

#1455000
1!

#1460000
0!

#1465000
1!

#1470000
0!

#1475000
1!

#1480000
0!

#1485000
1!

#1490000
0!

#1495000
1!

#1500000
0!
1"

#1505000
1!

#1510000
0!

#1515000
1!

#1520000
0!

#1525000
1!

#1530000
0!

#1535000
1!

#1540000
0!

#1545000
1!

#1550000
0!

#1555000
1!

#1560000
0!

#1565000
1!

#1570000
0!

#1575000
1!

#1580000
0!

#1585000
1!

#1590000
0!

#1595000
1!

#1600000
0!

#1605000
1!

#1610000
0!

#1615000
1!

#1620000
0!

#1625000
1!

#1630000
0!

#1635000
1!

#1640000
0!

#1645000
1!

#1650000
0!

#1655000
1!

#1660000
0!

#1665000
1!

#1670000
0!

#1675000
1!

#1680000
0!

#1685000
1!

#1690000
0!

#1695000
1!

#1700000
0!

#1705000
1!

#1710000
0!

#1715000
1!

#1720000
0!

#1725000
1!

#1730000
0!

#1735000
1!

#1740000
0!

#1745000
1!

#1750000
0!

#1755000
1!

#1760000
0!

#1765000
1!

#1770000
0!

#1775000
1!

#1780000
0!

#1785000
1!

#1790000
0!

#1795000
1!

#1800000
0!

#1805000
1!

#1810000
0!

#1815000
1!

#1820000
0!

#1825000
1!

#1830000
0!

#1835000
1!

#1840000
0!

#1845000
1!

#1850000
0!

#1855000
1!

#1860000
0!

#1865000
1!

#1870000
0!

#1875000
1!

#1880000
0!

#1885000
1!

#1890000
0!

#1895000
1!

#1900000
0!

#1905000
1!

#1910000
0!

#1915000
1!

#1920000
0!

#1925000
1!

#1930000
0!

#1935000
1!

#1940000
0!

#1945000
1!

#1950000
0!

#1955000
1!

#1960000
0!

#1965000
1!

#1970000
0!

#1975000
1!

#1980000
0!

#1985000
1!

#1990000
0!

#1995000
1!
1$

#2000000
0!

#2005000
1!
0$
b11 %

#2010000
0!

#2015000
1!

#2020000
0!

#2025000
1!

#2030000
0!

#2035000
1!

#2040000
0!

#2045000
1!

#2050000
0!

#2055000
1!

#2060000
0!

#2065000
1!

#2070000
0!

#2075000
1!

#2080000
0!

#2085000
1!

#2090000
0!

#2095000
1!

#2100000
0!

#2105000
1!

#2110000
0!

#2115000
1!

#2120000
0!

#2125000
1!

#2130000
0!

#2135000
1!

#2140000
0!

#2145000
1!

#2150000
0!

#2155000
1!

#2160000
0!

#2165000
1!

#2170000
0!

#2175000
1!

#2180000
0!

#2185000
1!

#2190000
0!

#2195000
1!

#2200000
0!

#2205000
1!

#2210000
0!

#2215000
1!

#2220000
0!

#2225000
1!

#2230000
0!

#2235000
1!

#2240000
0!

#2245000
1!

#2250000
0!

#2255000
1!

#2260000
0!

#2265000
1!

#2270000
0!

#2275000
1!

#2280000
0!

#2285000
1!

#2290000
0!

#2295000
1!

#2300000
0!

#2305000
1!

#2310000
0!

#2315000
1!

#2320000
0!

#2325000
1!

#2330000
0!

#2335000
1!

#2340000
0!

#2345000
1!

#2350000
0!

#2355000
1!

#2360000
0!

#2365000
1!

#2370000
0!

#2375000
1!

#2380000
0!

#2385000
1!

#2390000
0!

#2395000
1!

#2400000
0!

#2405000
1!

#2410000
0!

#2415000
1!

#2420000
0!

#2425000
1!

#2430000
0!

#2435000
1!

#2440000
0!

#2445000
1!

#2450000
0!

#2455000
1!

#2460000
0!

#2465000
1!

#2470000
0!

#2475000
1!

#2480000
0!

#2485000
1!

#2490000
0!

#2495000
1!

#2500000
0!

#2505000
1!

#2510000
0!

#2515000
1!

#2520000
0!

#2525000
1!

#2530000
0!

#2535000
1!

#2540000
0!

#2545000
1!

#2550000
0!

#2555000
1!

#2560000
0!

#2565000
1!

#2570000
0!

#2575000
1!

#2580000
0!

#2585000
1!

#2590000
0!

#2595000
1!

#2600000
0!

#2605000
1!

#2610000
0!

#2615000
1!

#2620000
0!

#2625000
1!

#2630000
0!

#2635000
1!

#2640000
0!

#2645000
1!

#2650000
0!

#2655000
1!

#2660000
0!

#2665000
1!

#2670000
0!

#2675000
1!

#2680000
0!

#2685000
1!

#2690000
0!

#2695000
1!

#2700000
0!

#2705000
1!

#2710000
0!

#2715000
1!

#2720000
0!

#2725000
1!

#2730000
0!

#2735000
1!

#2740000
0!

#2745000
1!

#2750000
0!

#2755000
1!

#2760000
0!

#2765000
1!

#2770000
0!

#2775000
1!

#2780000
0!

#2785000
1!

#2790000
0!

#2795000
1!

#2800000
0!

#2805000
1!

#2810000
0!

#2815000
1!

#2820000
0!

#2825000
1!

#2830000
0!

#2835000
1!

#2840000
0!

#2845000
1!

#2850000
0!

#2855000
1!

#2860000
0!

#2865000
1!

#2870000
0!

#2875000
1!

#2880000
0!

#2885000
1!

#2890000
0!

#2895000
1!

#2900000
0!

#2905000
1!

#2910000
0!

#2915000
1!

#2920000
0!

#2925000
1!

#2930000
0!

#2935000
1!

#2940000
0!

#2945000
1!

#2950000
0!

#2955000
1!

#2960000
0!

#2965000
1!

#2970000
0!

#2975000
1!

#2980000
0!

#2985000
1!

#2990000
0!

#2995000
1!
1$

#3000000
0!

#3005000
1!
0$
b111 %

